{"cameraMode":{"drawMode":0,"name":"Shaded","section":"Shading Mode"},"sceneLighting":true,"audioPlay":false,"sceneViewState":{"showFog":true,"showMaterialUpdate":false,"showSkybox":true,"showFlares":true,"showImageEffects":true,"showParticleSystems":true},"in2DMode":false,"pivot":{"x":1.3026914596557618,"y":6.159699440002441,"z":10.980469703674317},"rotation":{"x":-0.05268393084406853,"y":0.9248442053794861,"z":-0.13920719921588899,"w":-0.350012868642807},"size":11.844958305358887,"orthographic":false}